google/cloud/batch/__init__.py
google/cloud/batch/gapic_version.py
google/cloud/batch/py.typed
google/cloud/batch_v1/__init__.py
google/cloud/batch_v1/gapic_metadata.json
google/cloud/batch_v1/gapic_version.py
google/cloud/batch_v1/py.typed
google/cloud/batch_v1/services/__init__.py
google/cloud/batch_v1/services/batch_service/__init__.py
google/cloud/batch_v1/services/batch_service/async_client.py
google/cloud/batch_v1/services/batch_service/client.py
google/cloud/batch_v1/services/batch_service/pagers.py
google/cloud/batch_v1/services/batch_service/transports/__init__.py
google/cloud/batch_v1/services/batch_service/transports/base.py
google/cloud/batch_v1/services/batch_service/transports/grpc.py
google/cloud/batch_v1/services/batch_service/transports/grpc_asyncio.py
google/cloud/batch_v1/services/batch_service/transports/rest.py
google/cloud/batch_v1/services/batch_service/transports/rest_base.py
google/cloud/batch_v1/types/__init__.py
google/cloud/batch_v1/types/batch.py
google/cloud/batch_v1/types/job.py
google/cloud/batch_v1/types/task.py
google/cloud/batch_v1/types/volume.py
google/cloud/batch_v1alpha/__init__.py
google/cloud/batch_v1alpha/gapic_metadata.json
google/cloud/batch_v1alpha/gapic_version.py
google/cloud/batch_v1alpha/py.typed
google/cloud/batch_v1alpha/services/__init__.py
google/cloud/batch_v1alpha/services/batch_service/__init__.py
google/cloud/batch_v1alpha/services/batch_service/async_client.py
google/cloud/batch_v1alpha/services/batch_service/client.py
google/cloud/batch_v1alpha/services/batch_service/pagers.py
google/cloud/batch_v1alpha/services/batch_service/transports/__init__.py
google/cloud/batch_v1alpha/services/batch_service/transports/base.py
google/cloud/batch_v1alpha/services/batch_service/transports/grpc.py
google/cloud/batch_v1alpha/services/batch_service/transports/grpc_asyncio.py
google/cloud/batch_v1alpha/services/batch_service/transports/rest.py
google/cloud/batch_v1alpha/services/batch_service/transports/rest_base.py
google_cloud_batch-0.17.35.dist-info/LICENSE
google_cloud_batch-0.17.35.dist-info/METADATA
google_cloud_batch-0.17.35.dist-info/WHEEL
google_cloud_batch-0.17.35.dist-info/top_level.txt
google_cloud_batch-0.17.35.dist-info/RECORD
